meowmod/__init__.py
meowmod/__main__.py
meowmod/adb_handler.py
meowmod/config_manager.py
meowmod/csv_handler.py
meowmod/feature_handler.py
meowmod/game_data_getter.py
meowmod/helper.py
meowmod/item.py
meowmod/locale_handler.py
meowmod/managed_item.py
meowmod/parse_save.py
meowmod/patcher.py
meowmod/py.typed
meowmod/root_handler.py
meowmod/serialise_save.py
meowmod/server_handler.py
meowmod/updater.py
meowmod/user_info.py
meowmod/user_input_handler.py
meowmod/edits/__init__.py
meowmod/edits/basic/__init__.py
meowmod/edits/basic/basic_items.py
meowmod/edits/basic/catfruit.py
meowmod/edits/basic/catseyes.py
meowmod/edits/basic/ototo_base_mats.py
meowmod/edits/basic/talent_orbs.py
meowmod/edits/basic/talent_orbs_new.py
meowmod/edits/cats/__init__.py
meowmod/edits/cats/cat_helper.py
meowmod/edits/cats/cat_id_selector.py
meowmod/edits/cats/chara_drop.py
meowmod/edits/cats/clear_cat_guide.py
meowmod/edits/cats/evolve_cats.py
meowmod/edits/cats/get_remove_cats.py
meowmod/edits/cats/talents.py
meowmod/edits/cats/upgrade_blue.py
meowmod/edits/cats/upgrade_cats.py
meowmod/edits/gamototo/__init__.py
meowmod/edits/gamototo/fix_gamatoto.py
meowmod/edits/gamototo/gamatoto_xp.py
meowmod/edits/gamototo/helpers.py
meowmod/edits/gamototo/ototo_cat_cannon.py
meowmod/edits/levels/__init__.py
meowmod/edits/levels/aku.py
meowmod/edits/levels/allow_filibuster_clearing.py
meowmod/edits/levels/behemoth_culling.py
meowmod/edits/levels/clear_tutorial.py
meowmod/edits/levels/enigma_stages.py
meowmod/edits/levels/event_stages.py
meowmod/edits/levels/gauntlet.py
meowmod/edits/levels/itf_timed_scores.py
meowmod/edits/levels/legend_quest.py
meowmod/edits/levels/main_story.py
meowmod/edits/levels/outbreaks.py
meowmod/edits/levels/story_level_id_selector.py
meowmod/edits/levels/towers.py
meowmod/edits/levels/treasures.py
meowmod/edits/levels/uncanny.py
meowmod/edits/levels/unlock_aku_realm.py
meowmod/edits/levels/zerolegends.py
meowmod/edits/other/__init__.py
meowmod/edits/other/cat_shrine.py
meowmod-3.0.0.7.dist-info/METADATA
meowmod-3.0.0.7.dist-info/WHEEL
meowmod-3.0.0.7.dist-info/entry_points.txt
meowmod-3.0.0.7.dist-info/top_level.txt
meowmod-3.0.0.7.dist-info/RECORD
