Metadata-Version: 2.4
Name: meowmod
Version: 3.0.0.7
Summary: Battle Cats Save File Editor - 修改器套件
Author: 小孫孫
Author-email: sun1000526@gmail.com
Requires-Python: >=3.7
Requires-Dist: colored==1.4.4
Requires-Dist: pyyaml==6.0.2
Requires-Dist: requests==2.32.3
Requires-Dist: python-dateutil
Dynamic: author
Dynamic: author-email
Dynamic: requires-dist
Dynamic: requires-python
Dynamic: summary
